{"type":"root","label":null,"url":"","children":[{"type":"category","label":"Inicio","url":"http:\/\/localhost\/mx\/","children":[],"open_in_new_window":false,"image_urls":[],"page_identifier":"category-2","current":false,"depth":1},{"type":"cms-page","label":"Servicios","url":"http:\/\/localhost\/mx\/content\/6-servicios","children":[],"open_in_new_window":false,"image_urls":[],"page_identifier":"cms-page-6","depth":1},{"type":"cms-page","label":"Sobre nosotros","url":"http:\/\/localhost\/mx\/content\/4-sobre-nosotros","children":[],"open_in_new_window":false,"image_urls":[],"page_identifier":"cms-page-4","depth":1},{"type":"cms-page","label":"cont\u00e1ctanos","url":"http:\/\/localhost\/mx\/content\/7-cantactanos","children":[],"open_in_new_window":false,"image_urls":[],"page_identifier":"cms-page-7","depth":1}],"open_in_new_window":false,"image_urls":[],"page_identifier":null,"depth":0}